brandmint_mcp/__init__.py
brandmint_mcp/brandmint.py
brandmint_mcp/server_sse.py
brandmint_mcp/server_stdio.py
brandmint_mcp-0.0.7.dist-info/METADATA
brandmint_mcp-0.0.7.dist-info/WHEEL
brandmint_mcp-0.0.7.dist-info/entry_points.txt
brandmint_mcp-0.0.7.dist-info/top_level.txt
brandmint_mcp-0.0.7.dist-info/RECORD
