Metadata-Version: 2.4
Name: brandmint-mcp
Version: 0.0.7
Summary: brandmint.ai MCP tool
Requires-Python: >=3.10
Requires-Dist: mcp
Requires-Dist: google-adk
Requires-Dist: python-dotenv
Requires-Dist: deprecated
